LICENSE
MANIFEST.in
README.md
setup.cfg
setup.py
activities/__init__.py
activities/constants.py
activities/context_processors.py
activities/forms.py
activities/http.py
activities/managers.py
activities/models.py
activities/urls.py
activities/utils.py
activities/views.py
activities/migrations/0001_initial.py
activities/migrations/__init__.py
activities/mixins/__init__.py
activities/mixins/views.py
activities/static/activities/js/activities.js
activities/static/activities/less/activities.css
activities/static/activities/less/activities.less
activities/templates/activities/base_activities.html
activities/templates/activities/base_activity.html
activities/templates/activities/delete_activity.html
activities/templates/activities/delete_activity_reply.html
activities/templates/activities/edit_activity.html
activities/templates/activities/edit_activity_reply.html
activities/templates/activities/view_activities.html
activities/templates/activities/view_activity.html
activities/templates/activities/view_activity_replies.html
activities/templates/activities/view_activity_reply.html
activities/templates/activities/snippets/activities.html
activities/templates/activities/snippets/activity.html
activities/templatetags/__init__.py
activities/templatetags/activity_tags.py
django_activities.egg-info/PKG-INFO
django_activities.egg-info/SOURCES.txt
django_activities.egg-info/dependency_links.txt
django_activities.egg-info/not-zip-safe
django_activities.egg-info/top_level.txt